tp/__init__.py
tp/gremlin.py
pyjanusgraph-0.0.1a2.dist-info/LICENSE
pyjanusgraph-0.0.1a2.dist-info/METADATA
pyjanusgraph-0.0.1a2.dist-info/WHEEL
pyjanusgraph-0.0.1a2.dist-info/top_level.txt
pyjanusgraph-0.0.1a2.dist-info/RECORD
