Metadata-Version: 2.1
Name: pyjanusgraph
Version: 0.0.1a2
Summary: Python janusgraph utility library
Home-page: https://github.com/BITPlan/pyjanusgraph
Author: Wolfgang Fahl
Maintainer: Wolfgang Fahl
License: Apache License
Platform: UNKNOWN
